topsis_kriti_102303032/__init__.py
topsis_kriti_102303032/topsis.py
topsis_kriti_102303032-1.0.0.dist-info/METADATA
topsis_kriti_102303032-1.0.0.dist-info/WHEEL
topsis_kriti_102303032-1.0.0.dist-info/entry_points.txt
topsis_kriti_102303032-1.0.0.dist-info/top_level.txt
topsis_kriti_102303032-1.0.0.dist-info/RECORD
