Metadata-Version: 2.4
Name: Topsis-Kriti-102303032
Version: 1.0.0
Summary: TOPSIS implementation using Python
Author: Kriti
Author-email: kritigoyal0108@email.com
Classifier: Programming Language :: Python :: 3
Classifier: License :: OSI Approved :: MIT License
Classifier: Operating System :: OS Independent
Requires-Dist: pandas
Requires-Dist: numpy
Dynamic: author
Dynamic: author-email
Dynamic: classifier
Dynamic: description
Dynamic: description-content-type
Dynamic: requires-dist
Dynamic: summary
